canonical_domain/__init__.py
canonical_domain/apps.py
canonical_domain/middleware.py
django_canonical_domain-0.11.0.dist-info/LICENSE
django_canonical_domain-0.11.0.dist-info/METADATA
django_canonical_domain-0.11.0.dist-info/WHEEL
django_canonical_domain-0.11.0.dist-info/top_level.txt
django_canonical_domain-0.11.0.dist-info/RECORD
