Metadata-Version: 2.1
Name: django_canonical_domain
Version: 0.11.0
Summary: Canonical domain redirection for Django
Home-page: https://github.com/matthiask/django-canonical-domain/
Author: Matthias Kestenholz
Author-email: mk@feinheit.ch
License: BSD-3-Clause
Platform: OS Independent
Classifier: Development Status :: 5 - Production/Stable
Classifier: Environment :: Web Environment
Classifier: Framework :: Django
Classifier: Intended Audience :: Developers
Classifier: License :: OSI Approved :: BSD License
Classifier: Operating System :: OS Independent
Classifier: Programming Language :: Python
Classifier: Programming Language :: Python :: 3
Classifier: Programming Language :: Python :: 3 :: Only
Classifier: Programming Language :: Python :: 3.10
Classifier: Programming Language :: Python :: 3.11
Classifier: Programming Language :: Python :: 3.12
Classifier: Topic :: Internet :: WWW/HTTP :: Dynamic Content
Classifier: Topic :: Software Development
Classifier: Topic :: Software Development :: Libraries :: Application Frameworks
Requires-Python: >=3.10
License-File: LICENSE
Requires-Dist: Django >=4.2
Provides-Extra: tests
Requires-Dist: coverage ; extra == 'tests'
